setup.py
pils/__init__.py
pils/aws.py
pils/pils.py
pils.egg-info/PKG-INFO
pils.egg-info/SOURCES.txt
pils.egg-info/dependency_links.txt
pils.egg-info/requires.txt
pils.egg-info/top_level.txt
pils.egg-info/zip-safe