Metadata-Version: 1.0
Name: pils
Version: 0.1.23-30
Summary: PILS - Python uTILS
Home-page: https://github.com/ImmobilienScout24/pils
Author: UNKNOWN
Author-email: UNKNOWN
License: Apache License 2.0
Platform: UNKNOWN
Classifier: Development Status :: 3 - Alpha
Classifier: Programming Language :: Python
